syncstream/__init__.py
syncstream/base.py
syncstream/file.py
syncstream/host.py
syncstream/mproc.py
syncstream/utils.py
syncstream/version.py
syncstream/webtools.py
syncstream-1.2.2.dist-info/LICENSE
syncstream-1.2.2.dist-info/METADATA
syncstream-1.2.2.dist-info/WHEEL
syncstream-1.2.2.dist-info/top_level.txt
syncstream-1.2.2.dist-info/zip-safe
syncstream-1.2.2.dist-info/RECORD
